__init__.py
qcew.py
qcew-1.0.4.dist-info/LICENSE
qcew-1.0.4.dist-info/METADATA
qcew-1.0.4.dist-info/WHEEL
qcew-1.0.4.dist-info/top_level.txt
qcew-1.0.4.dist-info/RECORD
