Metadata-Version: 2.1
Name: qcew
Version: 1.0.4
Summary: A package for retrieving Quarterly Census of Employment and Wages (QCEW) data.
Home-page: https://github.com/TrentLThompson/qcew
Author: Trent Thompson
Author-email: 808trent@gmail.com
Keywords: QCEW,BLS,employment,wages,statistics
Classifier: Development Status :: 5 - Production/Stable
Classifier: Programming Language :: Python :: 3.8
Classifier: Programming Language :: Python :: 3.9
Classifier: Programming Language :: Python :: 3.10
Classifier: Programming Language :: Python :: 3.11
Classifier: License :: OSI Approved :: MIT License
Classifier: Operating System :: OS Independent
Requires-Python: >= 3.8
License-File: LICENSE
